{
    "model_name": "CP_effectors_2023-12-04",
    "model_type": "cellpose",
    "pretrained": "/home/torro/Documents/GitHub/celldetective/celldetective/models/segmentation_effectors/CP_effectors",
    "spatial_calibration": 1.6666666666666667,
    "channel_option": [
        "live_nuclei_channel",
        "live_nuclei_channel"
    ],
    "normalization_percentile": [
        true,
        true
    ],
    "normalization_clip": [
        true,
        true
    ],
    "normalization_values": [
        [
            1.0,
            99.0
        ],
        [
            1.0,
            99.0
        ]
    ],
    "ds": [
        "/home/torro/Documents/Experiments/Neuroblastoma/annotations_effectors"
    ],
    "augmentation_factor": 1.0,
    "validation_split": 0.0,
    "learning_rate": 0.001,
    "batch_size": 1,
    "epochs": 12,
    "target_directory": "/home/torro/Documents/GitHub/celldetective/celldetective/models/segmentation_effectors"
}